atomgpt/__init__.py
atomgpt/data/__init__.py
atomgpt/data/dataset.py
atomgpt/examples/__init__.py
atomgpt/examples/forward_model/__init__.py
atomgpt/examples/forward_model/generate_sample_data_reg.py
atomgpt/forward_models/__init__.py
atomgpt/forward_models/forward_models.py
atomgpt/forward_models/forward_predict.py
atomgpt/inverse_models/__init__.py
atomgpt/inverse_models/_utils.py
atomgpt/inverse_models/custom_trainer.py
atomgpt/inverse_models/database_generator.py
atomgpt/inverse_models/dpo.py
atomgpt/inverse_models/gemma.py
atomgpt/inverse_models/gguf_loader.py
atomgpt/inverse_models/inverse_models.py
atomgpt/inverse_models/inverse_predict.py
atomgpt/inverse_models/llama.py
atomgpt/inverse_models/loader.py
atomgpt/inverse_models/mapper.py
atomgpt/inverse_models/mistral.py
atomgpt/inverse_models/qwen2.py
atomgpt/inverse_models/save.py
atomgpt/inverse_models/tokenizer_utils.py
atomgpt/inverse_models/utils.py
atomgpt/inverse_models/kernels/__init__.py
atomgpt/inverse_models/kernels/cross_entropy_loss.py
atomgpt/inverse_models/kernels/fast_lora.py
atomgpt/inverse_models/kernels/geglu.py
atomgpt/inverse_models/kernels/rms_layernorm.py
atomgpt/inverse_models/kernels/rope_embedding.py
atomgpt/inverse_models/kernels/swiglu.py
atomgpt/inverse_models/kernels/utils.py
atomgpt-2024.11.30.dist-info/LICENSE.rst
atomgpt-2024.11.30.dist-info/METADATA
atomgpt-2024.11.30.dist-info/WHEEL
atomgpt-2024.11.30.dist-info/entry_points.txt
atomgpt-2024.11.30.dist-info/top_level.txt
atomgpt-2024.11.30.dist-info/RECORD
