Metadata-Version: 2.2
Name: atomgpt
Version: 2024.11.30
Summary: atomgpt
Home-page: https://github.com/usnistgov/atomgpt
Author: Kamal Choudhary
Author-email: kamal.choudhary@nist.gov
Classifier: Programming Language :: Python :: 3
Classifier: License :: OSI Approved :: MIT License
Classifier: Operating System :: OS Independent
Requires-Python: >=3.8
License-File: LICENSE.rst
Requires-Dist: accelerate==0.31.0
Requires-Dist: aiohttp==3.9.5
Requires-Dist: aiosignal==1.3.1
Requires-Dist: alignn==2024.4.20
Requires-Dist: annotated-types==0.7.0
Requires-Dist: ase==3.23.0
Requires-Dist: async-timeout==4.0.3
Requires-Dist: attrs==23.2.0
Requires-Dist: autopep8==2.3.1
Requires-Dist: bitsandbytes==0.43.1
Requires-Dist: black==24.4.2
Requires-Dist: certifi==2024.6.2
Requires-Dist: cffi
Requires-Dist: chardet==3.0.4
Requires-Dist: charset-normalizer==3.3.2
Requires-Dist: click==8.1.7
Requires-Dist: contourpy==1.2.1
Requires-Dist: cycler==0.12.1
Requires-Dist: datasets==2.20.0
Requires-Dist: dgl==1.1.1
Requires-Dist: dill==0.3.8
Requires-Dist: docstring_parser==0.16
Requires-Dist: eval_type_backport==0.2.0
Requires-Dist: filelock
Requires-Dist: flake8==7.1.0
Requires-Dist: fonttools==4.53.0
Requires-Dist: frozenlist==1.4.1
Requires-Dist: fsspec==2024.5.0
Requires-Dist: gmpy2
Requires-Dist: huggingface-hub==0.23.4
Requires-Dist: idna==3.7
Requires-Dist: importlib_resources==6.4.0
Requires-Dist: jarvis-tools>=2024.4.30
Requires-Dist: Jinja2
Requires-Dist: joblib==1.4.2
Requires-Dist: kiwisolver==1.4.5
Requires-Dist: lmdb==1.4.1
Requires-Dist: markdown-it-py==3.0.0
Requires-Dist: MarkupSafe
Requires-Dist: matplotlib==3.9.0
Requires-Dist: mccabe==0.7.0
Requires-Dist: mdurl==0.1.2
Requires-Dist: mpmath
Requires-Dist: multidict==4.7.6
Requires-Dist: multiprocess==0.70.16
Requires-Dist: mypy-extensions==1.0.0
Requires-Dist: networkx
Requires-Dist: numpy==1.26.4
Requires-Dist: packaging==24.1
Requires-Dist: pandas==2.2.2
Requires-Dist: pathspec==0.12.1
Requires-Dist: peft==0.11.1
Requires-Dist: pillow==10.3.0
Requires-Dist: platformdirs==4.2.2
Requires-Dist: protobuf==3.20.3
Requires-Dist: psutil==6.0.0
Requires-Dist: pyarrow==16.1.0
Requires-Dist: pyarrow-hotfix==0.6
Requires-Dist: pycodestyle==2.12.0
Requires-Dist: pycparser
Requires-Dist: pydantic==2.7.4
Requires-Dist: pydantic-settings==2.3.3
Requires-Dist: pydantic_core==2.18.4
Requires-Dist: pydocstyle==6.3.0
Requires-Dist: pyflakes==3.2.0
Requires-Dist: Pygments==2.18.0
Requires-Dist: pyparsing==2.4.7
Requires-Dist: python-dateutil==2.9.0.post0
Requires-Dist: python-dotenv==1.0.1
Requires-Dist: pytz==2024.1
Requires-Dist: PyYAML
Requires-Dist: regex==2024.5.15
Requires-Dist: requests==2.32.3
Requires-Dist: rich==13.7.1
Requires-Dist: safetensors==0.4.3
Requires-Dist: scikit-learn==1.5.0
Requires-Dist: scipy==1.13.1
Requires-Dist: sentencepiece==0.2.0
Requires-Dist: shtab==1.7.1
Requires-Dist: six==1.16.0
Requires-Dist: snowballstemmer==2.2.0
Requires-Dist: spglib==2.4.0
Requires-Dist: sympy
Requires-Dist: threadpoolctl==3.5.0
Requires-Dist: tokenizers==0.19.1
Requires-Dist: tomli==2.0.1
Requires-Dist: toolz==0.12.1
Requires-Dist: torch==2.2.2
Requires-Dist: torchdata==0.7.1
Requires-Dist: tqdm==4.66.4
Requires-Dist: transformers==4.41.2
Requires-Dist: triton==2.2.0
Requires-Dist: trl==0.8.6
Requires-Dist: typing_extensions
Requires-Dist: tyro==0.8.4
Requires-Dist: tzdata==2024.1
Requires-Dist: urllib3==2.2.2
Requires-Dist: xformers==0.0.25.post1
Requires-Dist: xmltodict==0.13.0
Requires-Dist: xxhash==3.4.1
Requires-Dist: yarl==1.9.4
Requires-Dist: zipp==3.19.2
Dynamic: author
Dynamic: author-email
Dynamic: classifier
Dynamic: description
Dynamic: description-content-type
Dynamic: home-page
Dynamic: requires-dist
Dynamic: requires-python
Dynamic: summary
